hello.py
llm_context_manager-0.1.0.dist-info/licenses/LICENSE
llm_context_manager-0.1.0.dist-info/METADATA
llm_context_manager-0.1.0.dist-info/WHEEL
llm_context_manager-0.1.0.dist-info/top_level.txt
llm_context_manager-0.1.0.dist-info/RECORD
